sqlaltery/__init__.py
sqlaltery/command.py
sqlaltery/compare.py
sqlaltery/migration.py
sqlaltery/ops.py
sqlaltery/render.py
sqlaltery/util.py
sqlaltery-0.5.7.dist-info/METADATA
sqlaltery-0.5.7.dist-info/WHEEL
sqlaltery-0.5.7.dist-info/top_level.txt
sqlaltery-0.5.7.dist-info/RECORD
