Metadata-Version: 2.4
Name: sqlaltery
Version: 0.5.7
Summary: A migration library for SQLAlchemy
Author: valtron
License-Expression: MIT
Project-URL: Repository, https://gitlab.com/valtron/sqlaltery
Classifier: Programming Language :: Python :: 3 :: Only
Classifier: Programming Language :: Python :: 3.10
Classifier: Programming Language :: Python :: 3.11
Classifier: Programming Language :: Python :: 3.12
Classifier: Programming Language :: Python :: 3.13
Classifier: Programming Language :: Python :: 3.14
Classifier: Operating System :: OS Independent
Requires-Python: ~=3.10
Requires-Dist: sqlalchemy~=2.0
Requires-Dist: alembic~=1.13
